pco_calendar/__init__.py
pco_calendar/api.py
pco_calendar/calendar.py
pco_calendar/py.typed
pco_calendar-0.1.2.dist-info/WHEEL
pco_calendar-0.1.2.dist-info/METADATA
pco_calendar-0.1.2.dist-info/RECORD
