Metadata-Version: 2.3
Name: pco-calendar
Version: 0.1.2
Summary: Add your description here
Author: Dark Decoy
Author-email: Dark Decoy <darkdecoy@notracking.space>
Requires-Dist: datetime>=5.5
Requires-Dist: python-dateutil>=2.9.0.post0
Requires-Dist: requests>=2.32.5
Requires-Python: >=3.12
